yaxls/__init__.py
yaxls/read.py
yaxls/write.py
yaxls-0.5.dist-info/WHEEL
yaxls-0.5.dist-info/METADATA
yaxls-0.5.dist-info/RECORD
