Metadata-Version: 1.2
Name: yaxls
Version: 0.5
Summary: Yet Another XLS library for read and write data files
Home-page: https://github.com/exedre/yaxls
License: UNKNOWN
Author: Emmanuele Somma
Author-email: exedre@gmail.com
Classifier: License :: OSI Approved :: MIT License
